{"time":{"updated":"Jun 16, 2022 00:12:00 UTC","updatedISO":"2022-06-16T00:12:00+00:00","updateduk":"Jun 16, 2022 at 01:12 BST"},"disclaimer":"This data was produced from the CoinDesk Bitcoin Price Index (USD). Non-USD currency data converted using hourly conversion rate from openexchangerates.org","chartName":"Bitcoin","bpi":{"USD":{"code":"USD","symbol":"&#36;","rate":"22,670.0923","description":"United States Dollar","rate_float":22670.0923},"GBP":{"code":"GBP","symbol":"&pound;","rate":"18,406.2787","description":"British Pound Sterling","rate_float":18406.2787},"EUR":{"code":"EUR","symbol":"&euro;","rate":"21,549.5097","description":"Euro","rate_float":21549.5097},"CNY":{"code":"CNY","symbol":"&yen;","rate":"40,202.5000","description":"Chinese Yuan","rate_float":40202.5}}}