{"time":{"updated":"Jun 8, 2021 01:02:00 UTC","updatedISO":"2021-06-08T01:02:00+00:00","updateduk":"Jun 8, 2021 at 02:02 BST"},"disclaimer":"This data was produced from the CoinDesk Bitcoin Price Index (USD). Non-USD currency data converted using hourly conversion rate from openexchangerates.org","chartName":"Bitcoin","bpi":{"USD":{"code":"USD","symbol":"&#36;","rate":"33,736.8165","description":"United States Dollar","rate_float":33736.8165},"GBP":{"code":"GBP","symbol":"&pound;","rate":"23,799.2323","description":"British Pound Sterling","rate_float":23799.2323},"EUR":{"code":"EUR","symbol":"&euro;","rate":"27,670.9369","description":"Euro","rate_float":27670.9369},"CNY":{"code":"CNY","symbol":"&yen;","rate":"40,202.5000","description":"Chinese Yuan","rate_float":40202.5}}}