{"time":{"updated":"Aug 11, 2021 00:42:00 UTC","updatedISO":"2021-08-11T00:42:00+00:00","updateduk":"Aug 11, 2021 at 01:42 BST"},"disclaimer":"This data was produced from the CoinDesk Bitcoin Price Index (USD). Non-USD currency data converted using hourly conversion rate from openexchangerates.org","chartName":"Bitcoin","bpi":{"USD":{"code":"USD","symbol":"&#36;","rate":"45,705.0902","description":"United States Dollar","rate_float":45705.0902},"GBP":{"code":"GBP","symbol":"&pound;","rate":"33,034.4051","description":"British Pound Sterling","rate_float":33034.4051},"EUR":{"code":"EUR","symbol":"&euro;","rate":"38,998.4166","description":"Euro","rate_float":38998.4166},"CNY":{"code":"CNY","symbol":"&yen;","rate":"40,202.5000","description":"Chinese Yuan","rate_float":40202.5}}}