{"time":{"updated":"Jan 29, 2023 00:12:00 UTC","updatedISO":"2023-01-29T00:12:00+00:00","updateduk":"Jan 29, 2023 at 00:12 GMT"},"disclaimer":"This data was produced from the CoinDesk Bitcoin Price Index (USD). Non-USD currency data converted using hourly conversion rate from openexchangerates.org","chartName":"Bitcoin","bpi":{"USD":{"code":"USD","symbol":"&#36;","rate":"23,019.4403","description":"United States Dollar","rate_float":23019.4403},"GBP":{"code":"GBP","symbol":"&pound;","rate":"19,234.8602","description":"British Pound Sterling","rate_float":19234.8602},"EUR":{"code":"EUR","symbol":"&euro;","rate":"22,424.2957","description":"Euro","rate_float":22424.2957},"CNY":{"code":"CNY","symbol":"&yen;","rate":"40,202.5000","description":"Chinese Yuan","rate_float":40202.5}}}