{"time":{"updated":"Jan 4, 2025 00:14:52 UTC","updatedISO":"2025-01-04T00:14:52+00:00","updateduk":"Jan 4, 2025 at 00:14 GMT"},"disclaimer":"This data was produced from the CoinDesk Bitcoin Price Index (USD). Non-USD currency data converted using hourly conversion rate from openexchangerates.org","chartName":"Bitcoin","bpi":{"USD":{"code":"USD","symbol":"&#36;","rate":"99,056.396","description":"United States Dollar","rate_float":99056.3963},"GBP":{"code":"GBP","symbol":"&pound;","rate":"78,995.495","description":"British Pound Sterling","rate_float":78995.4949},"EUR":{"code":"EUR","symbol":"&euro;","rate":"95,031.834","description":"Euro","rate_float":95031.834},"CNY":{"code":"CNY","symbol":"&yen;","rate":"722,973.014","description":"Chinese Yuan","rate_float":722973.0143}}}